alectiocli/__init__.py
alectiocli/main.py
alectiocli/src/__init__.py
alectiocli/src/config.py
alectiocli/src/console.py
alectiocli/src/experiment/__init__.py
alectiocli/src/experiment/experiment.py
alectiocli/src/experiment/helper.py
alectiocli/src/hybrid_labeling/helper.py
alectiocli/src/hybrid_labeling/hybrid_labeling.py
alectiocli/src/hybrid_labeling/marketplace_recommendation.py
alectiocli/src/login.py
alectiocli/src/project/__init__.py
alectiocli/src/project/delete_project.py
alectiocli/src/project/helper.py
alectiocli/src/project/project.py
alectiocli/src/project/project_list.py
alectiocli/src/test_code.py
alectiocli/src/utils.py
alectiocli-0.1.4.dist-info/entry_points.txt
alectiocli-0.1.4.dist-info/WHEEL
alectiocli-0.1.4.dist-info/METADATA
alectiocli-0.1.4.dist-info/RECORD
