Metadata-Version: 2.1
Name: alectiocli
Version: 0.1.4
Summary: 
Author: Adwitiya
Author-email: adwitiya.trivedi@alectio.com
Requires-Python: >=3.7,<4.0
Classifier: Programming Language :: Python :: 3
Classifier: Programming Language :: Python :: 3.10
Classifier: Programming Language :: Python :: 3.7
Classifier: Programming Language :: Python :: 3.8
Classifier: Programming Language :: Python :: 3.9
Requires-Dist: PyYAML (>=6.0,<7.0)
Requires-Dist: alectio-sdk (>=0.6.21,<0.7.0)
Requires-Dist: inquirer (>=2.9.2,<3.0.0)
Requires-Dist: pyfiglet (>=0.8.post1,<0.9)
Requires-Dist: requests (>=2.27.1,<3.0.0)
Requires-Dist: rich (>=12.2.0,<13.0.0)
Requires-Dist: ruamel.yaml (>=0.17.21,<0.18.0)
Requires-Dist: termcolor (>=1.1.0,<2.0.0)
Requires-Dist: typer[all] (>=0.4.0,<0.5.0)
